{
  "uri" : "local://thz-WzcNva83W4ovN3z589/",
  "name" : "common-univ Mgt Concept",
  "category" : "",
  "parent" : "local://-CV-HHtXHHByeKkIDfuo2A/",
  "flags" : "U",
  "lvars" : [ ],
  "vars" : [ {
    "name" : "_repo_repoUri",
    "expr" : {
      "str" : "/common/univ/"
    }
  }, {
    "name" : "_repo_gitHubRepo",
    "expr" : {
      "str" : "univ"
    }
  }, {
    "name" : "_repo_gitHubBranch",
    "expr" : {
      "str" : "master"
    }
  }, {
    "name" : "_repo_gitHubUsername",
    "expr" : {
      "str" : "conceptjs"
    }
  }, {
    "name" : "_repo_lastSyncAction",
    "expr" : {
      "str" : "push"
    }
  }, {
    "name" : "_repo_lastSyncTime",
    "expr" : {
      "str" : "2015-02-20T18:53:51.409Z"
    }
  }, {
    "name" : "repo",
    "expr" : {
      "concept" : "/common/core/NR8d-ezEsVB0v465tpkyi3/",
      "bindings" : {
        "repoUri" : "_repo_repoUri",
        "gitHubRepo" : "_repo_gitHubRepo",
        "gitHubBranch" : "_repo_gitHubBranch",
        "gitHubUsername" : "_repo_gitHubUsername",
        "lastSyncAction" : "_repo_lastSyncAction",
        "lastSyncTime" : "_repo_lastSyncTime"
      }
    }
  } ],
  "isas" : [ {
    "var" : "repo"
  } ],
  "isLambda" : false
}